.DS_Store
swachhdata/.DS_Store
swachhdata/__init__.py
swachhdata/compose/__init__.py
swachhdata/compose/core.py
swachhdata/image/__init__.py
swachhdata/image/_image.py
swachhdata/text/__init__.py
swachhdata/text/base.py
swachhdata/text/pipeline.py
swachhdata/text/recast.py
swachhdata/utils/__init__.py
swachhdata/utils/exceptions.py
swachhdata/utils/probe.py
swachhdata/utils/recast.py
swachhdata/utils/tools.py
swachhdata/utils/verify.py
swachhdata-2.0.2.dist-info/LICENSE.txt
swachhdata-2.0.2.dist-info/METADATA
swachhdata-2.0.2.dist-info/WHEEL
swachhdata-2.0.2.dist-info/top_level.txt
swachhdata-2.0.2.dist-info/RECORD
