Metadata-Version: 2.1
Name: swachhdata
Version: 2.0.2
Summary: Data cleaning made easy with swachhdata
Home-page: https://swachhdata.readthedocs.io/
Author: Kritik Seth
Author-email: sethkritik@gmail.com
Classifier: Natural Language :: English
Classifier: License :: OSI Approved :: Mozilla Public License 2.0 (MPL 2.0)
Classifier: Operating System :: OS Independent
Classifier: Development Status :: 5 - Production/Stable
License-File: LICENSE.txt
Requires-Dist: regex (>=2019.12.20)
Requires-Dist: pandas (>=1.1.4)
Requires-Dist: tqdm (>=4.41.1)
Requires-Dist: beautifulsoup4 (>=4.6.3)
Requires-Dist: html5lib (>=1.0.1)
Requires-Dist: contractions (>=0.0.25)
Requires-Dist: nltk (>=3.6.5)
Requires-Dist: spacy (>=2.2.4)
Requires-Dist: gensim (>=3.6.0)
Requires-Dist: num2words (>=0.5.10)
Requires-Dist: opencv-python (>=4.1.2.30)
Requires-Dist: emoji (>=2.2.0)
